orion5/__init__.py
orion5/orion5.py
orion5/orion5_client.py
orion5/orion5_serial.py
orion5/upgrade.py
orion5/version.py
orion5/orion5_math/__init__.py
orion5/orion5_math/ikinematics.py
orion5/orion5_math/orion5_math.py
orion5/utils/__init__.py
orion5/utils/firmware_updater.py
orion5/utils/general.py
orion5/utils/helpers.py
rawrobotics_orion5-1.5.6.dist-info/METADATA
rawrobotics_orion5-1.5.6.dist-info/WHEEL
rawrobotics_orion5-1.5.6.dist-info/top_level.txt
rawrobotics_orion5-1.5.6.dist-info/RECORD
