Metadata-Version: 2.1
Name: rawrobotics-orion5
Version: 1.5.6
Summary: Python libraries for the Orion5 robotic arm from RAWrobotics.
Home-page: https://github.com/rawrobotics/orion5
Author: RAWrobotics Pty. Ltd.
Author-email: info@rawrobotics.com.au
License: UNKNOWN
Download-URL: https://github.com/rawrobotics/orion5/releases/latest
Project-URL: Documentation, https://docs.rawrobotics.com
Project-URL: Source, https://github.com/rawrobotics/orion5
Project-URL: Tracker, https://github.com/rawrobotics/orion5/issues
Keywords: orion5 robotics rawrobotics robot arm
Platform: UNKNOWN
Classifier: Development Status :: 5 - Production/Stable
Classifier: License :: OSI Approved :: MIT License
Classifier: Programming Language :: Python :: 3
Requires-Python: >=3
Requires-Dist: pyserial
